hlk_sw16/__init__.py
hlk_sw16/protocol.py
hlk_sw16-0.0.9.dist-info/LICENSE
hlk_sw16-0.0.9.dist-info/METADATA
hlk_sw16-0.0.9.dist-info/WHEEL
hlk_sw16-0.0.9.dist-info/top_level.txt
hlk_sw16-0.0.9.dist-info/RECORD
