Metadata-Version: 1.0
Name: hlk-sw16
Version: 0.0.9
Summary: Python client for HLK-SW16
Home-page: https://github.com/jameshilliard/hlk-sw16
Author: James Hilliard
Author-email: james.hilliard1@gmail.com
License: MIT
Platform: UNKNOWN
